fractal/__init__.py
fractal/py.typed
fractal/contrib/__init__.py
fractal/contrib/django/__init__.py
fractal/contrib/django/middleware.py
fractal/contrib/django/projectors.py
fractal/contrib/django/requirements.txt
fractal/contrib/fastapi/__init__.py
fractal/contrib/fastapi/install.py
fractal/contrib/fastapi/requirements.txt
fractal/contrib/fastapi/exceptions/__init__.py
fractal/contrib/fastapi/exceptions/error_message.py
fractal/contrib/fastapi/routers/__init__.py
fractal/contrib/fastapi/routers/default.py
fractal/contrib/fastapi/routers/tokens.py
fractal/contrib/fastapi/routers/domain/__init__.py
fractal/contrib/fastapi/routers/domain/models.py
fractal/contrib/fastapi/utils/__init__.py
fractal/contrib/fastapi/utils/json_encoder.py
fractal/contrib/gcp/__init__.py
fractal/contrib/gcp/firestore/__init__.py
fractal/contrib/gcp/firestore/event_store.py
fractal/contrib/gcp/firestore/requirements.txt
fractal/contrib/gcp/pubsub/__init__.py
fractal/contrib/gcp/pubsub/event_bus.py
fractal/contrib/gcp/pubsub/projectors.py
fractal/contrib/gcp/pubsub/requirements.txt
fractal/contrib/kafka/README.md
fractal/contrib/kafka/__init__.py
fractal/contrib/kafka/docker-compose.yml
fractal/contrib/kafka/event_bus.py
fractal/contrib/kafka/projectors.py
fractal/contrib/kafka/requirements.txt
fractal/contrib/rabbitmq/__init__.py
fractal/contrib/rabbitmq/event_bus.py
fractal/contrib/rabbitmq/projectors.py
fractal/contrib/rabbitmq/requirements.txt
fractal/contrib/rabbitmq/utils.py
fractal/core/__init__.py
fractal/core/command_bus/__init__.py
fractal/core/command_bus/command.py
fractal/core/command_bus/command_bus.py
fractal/core/command_bus/command_handler.py
fractal/core/command_bus/commands.py
fractal/core/event_sourcing/__init__.py
fractal/core/event_sourcing/event.py
fractal/core/event_sourcing/event_bus.py
fractal/core/event_sourcing/event_projector.py
fractal/core/event_sourcing/event_publisher.py
fractal/core/event_sourcing/event_store.py
fractal/core/event_sourcing/event_stream.py
fractal_toolkit-5.3.4.dist-info/licenses/LICENSE
fractal_toolkit-5.3.4.dist-info/WHEEL
fractal_toolkit-5.3.4.dist-info/METADATA
fractal_toolkit-5.3.4.dist-info/RECORD
