Metadata-Version: 2.4
Name: fractal-toolkit
Version: 5.3.4
Summary: Fractal is a scaffolding toolkit for building SOLID logic for your Python applications.
Home-page: https://github.com/douwevandermeij/fractal
Author: Douwe van der Meij
Author-email: douwe@karibu-online.nl
Requires-Python: >=3.8
Classifier: Development Status :: 3 - Alpha
Classifier: Environment :: Web Environment
Classifier: Intended Audience :: Developers
Classifier: License :: OSI Approved :: MIT License
Classifier: Operating System :: OS Independent
Classifier: Programming Language :: Python :: 3
Classifier: Programming Language :: Python
License-File: LICENSE
Requires-Dist: fractal-repositories
Requires-Dist: fractal-roles
Requires-Dist: fractal-specifications
Requires-Dist: fractal-tokens
Requires-Dist: python-dotenv
Requires-Dist: black ; extra == "test"
Requires-Dist: flake8 ; extra == "test"
Requires-Dist: isort ; extra == "test"
Provides-Extra: test
